{ "columns":0,
 "margin":0,
 "name":"tm-floating",
 "spacing":0,
 "terrains":[
        {
         "name":"Nothing",
         "tile":-1
        }, 
        {
         "name":"Green",
         "tile":0
        }, 
        {
         "name":"Dirt",
         "tile":107
        }, 
        {
         "name":"Bridge",
         "tile":246
        }, 
        {
         "name":"RockFace",
         "tile":220
        }, 
        {
         "name":"RockEdge",
         "tile":230
        }],
 "tilecount":280,
 "tileheight":16,
 "tiles":
    {
     "0":
        {
         "image":"floating\/se_1_000.png",
         "terrain":[1, 1, 1, 1]
        },
     "1":
        {
         "image":"floating\/se_1_001.png",
         "terrain":[1, 1, 1, 0]
        },
     "10":
        {
         "image":"floating\/se_1_010.png"
        },
     "100":
        {
         "image":"floating\/se_2_041.png"
        },
     "101":
        {
         "image":"floating\/se_2_042.png"
        },
     "102":
        {
         "image":"floating\/se_2_043.png"
        },
     "103":
        {
         "image":"floating\/se_2_044.png"
        },
     "104":
        {
         "image":"floating\/se_2_045.png"
        },
     "105":
        {
         "image":"floating\/se_2_046.png"
        },
     "106":
        {
         "image":"floating\/se_2_047.png"
        },
     "107":
        {
         "image":"floating\/se_3_000.png",
         "terrain":[2, 2, 2, 2]
        },
     "108":
        {
         "image":"floating\/se_3_001.png",
         "terrain":[2, 2, 2, 1]
        },
     "109":
        {
         "image":"floating\/se_3_002.png",
         "terrain":[2, 2, 1, 2]
        },
     "11":
        {
         "image":"floating\/se_1_011.png"
        },
     "110":
        {
         "image":"floating\/se_3_003.png",
         "terrain":[2, 1, 2, 2]
        },
     "111":
        {
         "image":"floating\/se_3_004.png",
         "terrain":[1, 2, 2, 2]
        },
     "112":
        {
         "image":"floating\/se_3_005.png"
        },
     "113":
        {
         "image":"floating\/se_3_006.png"
        },
     "114":
        {
         "image":"floating\/se_3_007.png"
        },
     "115":
        {
         "image":"floating\/se_3_008.png"
        },
     "116":
        {
         "image":"floating\/se_3_009.png"
        },
     "117":
        {
         "image":"floating\/se_3_010.png"
        },
     "118":
        {
         "image":"floating\/se_3_011.png"
        },
     "119":
        {
         "image":"floating\/se_3_012.png"
        },
     "12":
        {
         "image":"floating\/se_1_012.png"
        },
     "120":
        {
         "image":"floating\/se_3_013.png"
        },
     "121":
        {
         "image":"floating\/se_3_014.png"
        },
     "122":
        {
         "image":"floating\/se_3_015.png"
        },
     "123":
        {
         "image":"floating\/se_3_016.png",
         "terrain":[2, 1, 2, 1]
        },
     "124":
        {
         "image":"floating\/se_3_017.png",
         "terrain":[2, 2, 1, 1]
        },
     "125":
        {
         "image":"floating\/se_3_018.png",
         "terrain":[1, 2, 1, 2]
        },
     "126":
        {
         "image":"floating\/se_3_019.png",
         "terrain":[1, 1, 2, 2]
        },
     "127":
        {
         "image":"floating\/se_3_020.png",
         "terrain":[2, 1, 2, 1]
        },
     "128":
        {
         "image":"floating\/se_3_021.png"
        },
     "129":
        {
         "image":"floating\/se_3_022.png"
        },
     "13":
        {
         "image":"floating\/se_1_013.png"
        },
     "130":
        {
         "image":"floating\/se_3_023.png"
        },
     "131":
        {
         "image":"floating\/se_3_024.png"
        },
     "132":
        {
         "image":"floating\/se_3_025.png"
        },
     "133":
        {
         "image":"floating\/se_3_026.png"
        },
     "134":
        {
         "image":"floating\/se_3_027.png"
        },
     "135":
        {
         "image":"floating\/se_3_028.png"
        },
     "136":
        {
         "image":"floating\/se_3_029.png"
        },
     "137":
        {
         "image":"floating\/se_3_030.png"
        },
     "138":
        {
         "image":"floating\/se_3_031.png"
        },
     "139":
        {
         "image":"floating\/se_3_032.png"
        },
     "14":
        {
         "image":"floating\/se_1_014.png"
        },
     "140":
        {
         "image":"floating\/se_3_033.png"
        },
     "141":
        {
         "image":"floating\/se_3_034.png",
         "terrain":[2, 1, 1, 1]
        },
     "142":
        {
         "image":"floating\/se_3_035.png",
         "terrain":[1, 2, 1, 1]
        },
     "143":
        {
         "image":"floating\/se_3_036.png",
         "terrain":[1, 1, 1, 2]
        },
     "144":
        {
         "image":"floating\/se_3_037.png",
         "terrain":[1, 1, 2, 1]
        },
     "145":
        {
         "image":"floating\/se_3_038.png"
        },
     "146":
        {
         "image":"floating\/se_3_039.png"
        },
     "147":
        {
         "image":"floating\/se_3_040.png"
        },
     "148":
        {
         "image":"floating\/se_3_041.png"
        },
     "149":
        {
         "image":"floating\/se_3_042.png"
        },
     "15":
        {
         "image":"floating\/se_1_015.png"
        },
     "150":
        {
         "image":"floating\/se_3_043.png"
        },
     "151":
        {
         "image":"floating\/se_3_044.png"
        },
     "152":
        {
         "image":"floating\/se_3_045.png"
        },
     "153":
        {
         "image":"floating\/se_3_046.png"
        },
     "154":
        {
         "image":"floating\/se_3_047.png"
        },
     "155":
        {
         "image":"floating\/se_4_000.png"
        },
     "156":
        {
         "image":"floating\/se_4_001.png"
        },
     "157":
        {
         "image":"floating\/se_4_002.png"
        },
     "158":
        {
         "image":"floating\/se_4_003.png"
        },
     "159":
        {
         "image":"floating\/se_4_004.png"
        },
     "16":
        {
         "image":"floating\/se_1_016.png",
         "terrain":[1, 0, 1, 0]
        },
     "160":
        {
         "image":"floating\/se_4_005.png"
        },
     "161":
        {
         "image":"floating\/se_4_006.png"
        },
     "162":
        {
         "image":"floating\/se_4_007.png"
        },
     "163":
        {
         "image":"floating\/se_4_008.png"
        },
     "164":
        {
         "image":"floating\/se_4_009.png"
        },
     "165":
        {
         "image":"floating\/se_4_010.png"
        },
     "166":
        {
         "image":"floating\/se_4_011.png"
        },
     "167":
        {
         "image":"floating\/se_4_012.png"
        },
     "168":
        {
         "image":"floating\/se_4_013.png"
        },
     "169":
        {
         "image":"floating\/se_4_014.png"
        },
     "17":
        {
         "image":"floating\/se_1_017.png",
         "terrain":[1, 1, 0, 0]
        },
     "170":
        {
         "image":"floating\/se_4_015.png"
        },
     "171":
        {
         "image":"floating\/se_4_016.png"
        },
     "172":
        {
         "image":"floating\/se_4_017.png"
        },
     "173":
        {
         "image":"floating\/se_4_018.png"
        },
     "174":
        {
         "image":"floating\/se_4_019.png"
        },
     "175":
        {
         "image":"floating\/se_4_020.png"
        },
     "176":
        {
         "image":"floating\/se_4_021.png"
        },
     "177":
        {
         "image":"floating\/se_4_022.png"
        },
     "178":
        {
         "image":"floating\/se_4_023.png"
        },
     "179":
        {
         "image":"floating\/se_4_024.png"
        },
     "18":
        {
         "image":"floating\/se_1_018.png",
         "terrain":[0, 1, 0, 1]
        },
     "180":
        {
         "image":"floating\/se_4_025.png"
        },
     "181":
        {
         "image":"floating\/se_4_026.png"
        },
     "182":
        {
         "image":"floating\/se_4_027.png"
        },
     "183":
        {
         "image":"floating\/se_4_028.png"
        },
     "184":
        {
         "image":"floating\/se_4_029.png"
        },
     "185":
        {
         "image":"floating\/se_4_030.png"
        },
     "186":
        {
         "image":"floating\/se_4_031.png"
        },
     "187":
        {
         "image":"floating\/se_4_032.png"
        },
     "188":
        {
         "image":"floating\/se_4_033.png"
        },
     "189":
        {
         "image":"floating\/se_4_034.png"
        },
     "19":
        {
         "image":"floating\/se_1_019.png",
         "terrain":[0, 0, 1, 1]
        },
     "190":
        {
         "image":"floating\/se_4_035.png"
        },
     "191":
        {
         "image":"floating\/se_4_036.png"
        },
     "192":
        {
         "image":"floating\/se_4_037.png"
        },
     "193":
        {
         "image":"floating\/se_4_038.png"
        },
     "194":
        {
         "image":"floating\/se_4_039.png"
        },
     "195":
        {
         "image":"floating\/se_4_040.png"
        },
     "196":
        {
         "image":"floating\/se_4_041.png"
        },
     "197":
        {
         "image":"floating\/se_4_042.png"
        },
     "198":
        {
         "image":"floating\/se_4_043.png"
        },
     "199":
        {
         "image":"floating\/se_4_044.png"
        },
     "2":
        {
         "image":"floating\/se_1_002.png",
         "terrain":[1, 1, 0, 1]
        },
     "20":
        {
         "image":"floating\/se_1_020.png"
        },
     "200":
        {
         "image":"floating\/se_4_045.png"
        },
     "201":
        {
         "image":"floating\/se_4_046.png"
        },
     "202":
        {
         "image":"floating\/se_4_047.png"
        },
     "203":
        {
         "image":"floating\/se_4_048.png"
        },
     "204":
        {
         "image":"floating\/se_4_049.png"
        },
     "205":
        {
         "image":"floating\/se_4_050.png"
        },
     "206":
        {
         "image":"floating\/se_4_051.png"
        },
     "207":
        {
         "image":"floating\/se_4_052.png"
        },
     "208":
        {
         "image":"floating\/se_4_053.png"
        },
     "209":
        {
         "image":"floating\/se_4_054.png"
        },
     "21":
        {
         "image":"floating\/se_1_021.png"
        },
     "210":
        {
         "image":"floating\/se_4_055.png"
        },
     "211":
        {
         "image":"floating\/se_4_056.png"
        },
     "212":
        {
         "image":"floating\/se_4_057.png"
        },
     "213":
        {
         "image":"floating\/se_4_058.png"
        },
     "214":
        {
         "image":"floating\/se_4_059.png"
        },
     "215":
        {
         "image":"floating\/se_4_060.png"
        },
     "216":
        {
         "image":"floating\/se_4_061.png"
        },
     "217":
        {
         "image":"floating\/se_4_062.png"
        },
     "218":
        {
         "image":"floating\/se_5_000.png"
        },
     "219":
        {
         "image":"floating\/se_5_001.png",
         "terrain":[0, 0, 0, 4]
        },
     "22":
        {
         "image":"floating\/se_1_022.png"
        },
     "220":
        {
         "image":"floating\/se_5_002.png",
         "terrain":[0, 0, 4, 4]
        },
     "221":
        {
         "image":"floating\/se_5_003.png",
         "terrain":[0, 0, 4, 4]
        },
     "222":
        {
         "image":"floating\/se_5_004.png",
         "terrain":[0, 0, 4, 0]
        },
     "223":
        {
         "image":"floating\/se_5_005.png"
        },
     "224":
        {
         "image":"floating\/se_5_006.png"
        },
     "225":
        {
         "image":"floating\/se_5_007.png",
         "terrain":[0, 4, 0, 5]
        },
     "226":
        {
         "image":"floating\/se_5_008.png",
         "terrain":[4, 4, 5, 5]
        },
     "227":
        {
         "image":"floating\/se_5_009.png",
         "terrain":[4, 4, 5, 5]
        },
     "228":
        {
         "image":"floating\/se_5_010.png",
         "terrain":[4, 0, 5, 0]
        },
     "229":
        {
         "image":"floating\/se_5_012.png"
        },
     "23":
        {
         "image":"floating\/se_1_023.png"
        },
     "230":
        {
         "image":"floating\/se_5_013.png",
         "terrain":[0, 5, 0, 0]
        },
     "231":
        {
         "image":"floating\/se_5_014.png",
         "terrain":[5, 5, 0, 0]
        },
     "232":
        {
         "image":"floating\/se_5_015.png",
         "terrain":[5, 5, 0, 0]
        },
     "233":
        {
         "image":"floating\/se_5_016.png",
         "terrain":[5, 0, 0, 0]
        },
     "234":
        {
         "image":"floating\/se_6_000.png"
        },
     "235":
        {
         "image":"floating\/se_6_001.png"
        },
     "236":
        {
         "image":"floating\/se_6_002.png"
        },
     "237":
        {
         "image":"floating\/se_6_003.png"
        },
     "238":
        {
         "image":"floating\/se_6_004.png"
        },
     "239":
        {
         "image":"floating\/se_6_005.png"
        },
     "24":
        {
         "image":"floating\/se_1_024.png"
        },
     "240":
        {
         "image":"floating\/se_6_006.png"
        },
     "241":
        {
         "image":"floating\/se_6_007.png"
        },
     "242":
        {
         "image":"floating\/se_6_008.png"
        },
     "243":
        {
         "image":"floating\/se_6_009.png"
        },
     "244":
        {
         "image":"floating\/se_6_010.png"
        },
     "245":
        {
         "image":"floating\/se_6_011.png"
        },
     "246":
        {
         "image":"floating\/se_6_012.png",
         "terrain":[1, 3, 1, 3]
        },
     "247":
        {
         "image":"floating\/se_6_013.png",
         "terrain":[3, 1, 3, 1]
        },
     "248":
        {
         "image":"floating\/se_6_014.png",
         "terrain":[1, 1, 3, 3]
        },
     "249":
        {
         "image":"floating\/se_6_015.png",
         "terrain":[-1, 3, -1, 3]
        },
     "25":
        {
         "image":"floating\/se_1_025.png"
        },
     "250":
        {
         "image":"floating\/se_6_016.png",
         "terrain":[3, -1, 3, -1]
        },
     "251":
        {
         "image":"floating\/se_6_017.png",
         "terrain":[-1, -1, 3, 3]
        },
     "252":
        {
         "image":"floating\/se_6_018.png"
        },
     "253":
        {
         "image":"floating\/se_6_019.png"
        },
     "254":
        {
         "image":"floating\/se_6_020.png",
         "terrain":[3, 3, 1, 1]
        },
     "255":
        {
         "image":"floating\/se_6_023.png",
         "terrain":[3, 3, -1, -1]
        },
     "256":
        {
         "image":"floating\/se_6_024.png"
        },
     "257":
        {
         "image":"floating\/se_6_025.png"
        },
     "258":
        {
         "image":"floating\/se_6_026.png"
        },
     "259":
        {
         "image":"floating\/se_6_027.png"
        },
     "26":
        {
         "image":"floating\/se_1_026.png"
        },
     "260":
        {
         "image":"floating\/se_6_028.png"
        },
     "261":
        {
         "image":"floating\/se_6_029.png"
        },
     "262":
        {
         "image":"floating\/se_6_030.png"
        },
     "263":
        {
         "image":"floating\/se_6_031.png"
        },
     "264":
        {
         "image":"floating\/se_6_032.png"
        },
     "265":
        {
         "image":"floating\/se_6_033.png"
        },
     "266":
        {
         "image":"floating\/se_6_034.png"
        },
     "267":
        {
         "image":"floating\/se_6_035.png"
        },
     "268":
        {
         "image":"floating\/se_6_036.png"
        },
     "269":
        {
         "image":"floating\/se_6_037.png"
        },
     "27":
        {
         "image":"floating\/se_1_027.png"
        },
     "270":
        {
         "image":"floating\/se_6_038.png"
        },
     "271":
        {
         "image":"floating\/se_6_039.png"
        },
     "272":
        {
         "image":"floating\/se_6_040.png"
        },
     "273":
        {
         "image":"floating\/se_6_041.png"
        },
     "274":
        {
         "image":"floating\/se_6_043.png"
        },
     "275":
        {
         "image":"floating\/se_6_044.png"
        },
     "276":
        {
         "image":"floating\/se_6_045.png"
        },
     "277":
        {
         "image":"floating\/se_6_046.png"
        },
     "278":
        {
         "image":"floating\/se_6_047.png"
        },
     "279":
        {
         "image":"blank.png",
         "terrain":[0, 0, 0, 0]
        },
     "28":
        {
         "image":"floating\/se_1_028.png"
        },
     "29":
        {
         "image":"floating\/se_1_029.png"
        },
     "3":
        {
         "image":"floating\/se_1_003.png",
         "terrain":[1, 0, 1, 1]
        },
     "30":
        {
         "image":"floating\/se_1_030.png"
        },
     "31":
        {
         "image":"floating\/se_1_031.png"
        },
     "32":
        {
         "image":"floating\/se_1_032.png"
        },
     "33":
        {
         "image":"floating\/se_1_033.png"
        },
     "34":
        {
         "image":"floating\/se_1_034.png",
         "terrain":[1, 0, 0, 0]
        },
     "35":
        {
         "image":"floating\/se_1_035.png",
         "terrain":[0, 1, 0, 0]
        },
     "36":
        {
         "image":"floating\/se_1_036.png",
         "terrain":[0, 0, 0, 1]
        },
     "37":
        {
         "image":"floating\/se_1_037.png",
         "terrain":[0, 0, 1, 0]
        },
     "38":
        {
         "image":"floating\/se_1_038.png"
        },
     "39":
        {
         "image":"floating\/se_1_039.png"
        },
     "4":
        {
         "image":"floating\/se_1_004.png",
         "terrain":[0, 1, 1, 1]
        },
     "40":
        {
         "image":"floating\/se_1_040.png"
        },
     "41":
        {
         "image":"floating\/se_1_041.png"
        },
     "42":
        {
         "image":"floating\/se_1_042.png"
        },
     "43":
        {
         "image":"floating\/se_1_043.png"
        },
     "44":
        {
         "image":"floating\/se_1_044.png"
        },
     "45":
        {
         "image":"floating\/se_1_045.png"
        },
     "46":
        {
         "image":"floating\/se_1_046.png"
        },
     "47":
        {
         "image":"floating\/se_1_047.png"
        },
     "48":
        {
         "image":"floating\/se_1_048.png"
        },
     "49":
        {
         "image":"floating\/se_1_049.png"
        },
     "5":
        {
         "image":"floating\/se_1_005.png"
        },
     "50":
        {
         "image":"floating\/se_1_050.png"
        },
     "51":
        {
         "image":"floating\/se_1_051.png"
        },
     "52":
        {
         "image":"floating\/se_1_052.png",
         "terrain":[1, 1, 0, 0]
        },
     "53":
        {
         "image":"floating\/se_1_053.png"
        },
     "54":
        {
         "image":"floating\/se_1_056.png",
         "terrain":[-1, -1, 1, 1]
        },
     "55":
        {
         "image":"floating\/se_1_057.png",
         "terrain":[-1, -1, 1, 1]
        },
     "56":
        {
         "image":"floating\/se_1_058.png",
         "terrain":[-1, -1, 1, 1]
        },
     "57":
        {
         "image":"floating\/se_1_059.png",
         "terrain":[-1, -1, 1, 1]
        },
     "58":
        {
         "image":"floating\/se_1_060.png",
         "terrain":[0, 0, 1, 1]
        },
     "59":
        {
         "image":"floating\/se_2_000.png"
        },
     "6":
        {
         "image":"floating\/se_1_006.png"
        },
     "60":
        {
         "image":"floating\/se_2_001.png"
        },
     "61":
        {
         "image":"floating\/se_2_002.png"
        },
     "62":
        {
         "image":"floating\/se_2_003.png"
        },
     "63":
        {
         "image":"floating\/se_2_004.png"
        },
     "64":
        {
         "image":"floating\/se_2_005.png"
        },
     "65":
        {
         "image":"floating\/se_2_006.png"
        },
     "66":
        {
         "image":"floating\/se_2_007.png"
        },
     "67":
        {
         "image":"floating\/se_2_008.png"
        },
     "68":
        {
         "image":"floating\/se_2_009.png"
        },
     "69":
        {
         "image":"floating\/se_2_010.png"
        },
     "7":
        {
         "image":"floating\/se_1_007.png"
        },
     "70":
        {
         "image":"floating\/se_2_011.png"
        },
     "71":
        {
         "image":"floating\/se_2_012.png"
        },
     "72":
        {
         "image":"floating\/se_2_013.png"
        },
     "73":
        {
         "image":"floating\/se_2_014.png"
        },
     "74":
        {
         "image":"floating\/se_2_015.png"
        },
     "75":
        {
         "image":"floating\/se_2_016.png"
        },
     "76":
        {
         "image":"floating\/se_2_017.png"
        },
     "77":
        {
         "image":"floating\/se_2_018.png"
        },
     "78":
        {
         "image":"floating\/se_2_019.png"
        },
     "79":
        {
         "image":"floating\/se_2_020.png"
        },
     "8":
        {
         "image":"floating\/se_1_008.png"
        },
     "80":
        {
         "image":"floating\/se_2_021.png"
        },
     "81":
        {
         "image":"floating\/se_2_022.png"
        },
     "82":
        {
         "image":"floating\/se_2_023.png"
        },
     "83":
        {
         "image":"floating\/se_2_024.png"
        },
     "84":
        {
         "image":"floating\/se_2_025.png"
        },
     "85":
        {
         "image":"floating\/se_2_026.png"
        },
     "86":
        {
         "image":"floating\/se_2_027.png"
        },
     "87":
        {
         "image":"floating\/se_2_028.png"
        },
     "88":
        {
         "image":"floating\/se_2_029.png"
        },
     "89":
        {
         "image":"floating\/se_2_030.png"
        },
     "9":
        {
         "image":"floating\/se_1_009.png"
        },
     "90":
        {
         "image":"floating\/se_2_031.png"
        },
     "91":
        {
         "image":"floating\/se_2_032.png"
        },
     "92":
        {
         "image":"floating\/se_2_033.png"
        },
     "93":
        {
         "image":"floating\/se_2_034.png"
        },
     "94":
        {
         "image":"floating\/se_2_035.png"
        },
     "95":
        {
         "image":"floating\/se_2_036.png"
        },
     "96":
        {
         "image":"floating\/se_2_037.png"
        },
     "97":
        {
         "image":"floating\/se_2_038.png"
        },
     "98":
        {
         "image":"floating\/se_2_039.png"
        },
     "99":
        {
         "image":"floating\/se_2_040.png"
        }
    },
 "tilewidth":16
}